codifMorse.v
module codifMorse (num, morse, reset, ready);

    // A = num[3]
    // B = num[2]
    // C = num[1]
    // D = num [0]

    input reset;
    input ready;
    input wire[3:0] num;
    output reg[4:0] morse;

    always @ (reset) begin
        morse = 0;
    end
    always @ (ready) begin
        if (~reset) begin
          morse[4] = (~num[2] & num[1]) | (num[2] & ~num[1]) | (~num[3] & ~num[2] & num[0]);
          morse[3] = (~num[2] & num[1]) | (num[1] & ~num[0]) | (num[2] & ~num[1]);
          morse[2] = num[2] | (num[1] & num[0]);
          morse[1] = num[2] | (num[3] & ~num[0]);
          morse[0] = num[3] | (num[2] & num[0]) | (num[2] & num[1]);

        end
    end
endmodule // divisivel

module demuxSegmento (controle, ponto, traco);

    input wire controle;
    output wire ponto, traco;

    assign ponto = controle;
    assign traco = ~controle;

endmodule

testbench.v
`include "codifMorse.v"

module testbench ();
    reg[3:0] num;
    reg rst, rdy;
    wire[4:0] morse;

    codifMorse codificador (.num(num), .reset(rst), .ready(rdy), .morse(morse));

    initial begin
      $dumpfile("codifMorse.vcd");
      $dumpvars(0, testbench);
      $display("Equivalente em morse (0 = Traço, 1 = Ponto)? ");
      $monitor("%d = %b %b %b %b %b", num, morse[0], morse[1], morse[2], morse[3], morse[4]);

          rst = 1;
      #1; rst = 0;
      #1; rdy = 0; num = 1; rdy = 1;
      #1; rdy = 0; num = 2; rdy = 1;
      #1; rdy = 0; num = 3; rdy = 1;
      #1; rdy = 0; num = 4; rdy = 1;
      #1; rdy = 0; num = 5; rdy = 1;
      #1; rdy = 0; num = 6; rdy = 1;
      #1; rdy = 0; num = 7; rdy = 1;
      #1; rdy = 0; num = 8; rdy = 1;
      #1; rdy = 0; num = 9; rdy = 1;
      #1; rdy = 0; num = 0; rdy = 1;
      #1;

      $finish;

    end
endmodule // testbench

codifMorse.vcd
$date
	Wed Oct  3 10:36:37 2018
$end
$version
	Icarus Verilog
$end
$timescale
	1s
$end
$scope module testbench $end
$var wire 5 ! morse [4:0] $end
$var reg 4 " num [3:0] $end
$var reg 1 # rdy $end
$var reg 1 $ rst $end
$scope module codificador $end
$var wire 4 % num [3:0] $end
$var wire 1 # ready $end
$var wire 1 $ reset $end
$var reg 5 & morse [4:0] $end
$upscope $end
$upscope $end
$enddefinitions $end
#0
$dumpvars
b0 &
bx %
1$
x#
bx "
b0 !
$end
#1
0$
#2
b1 !
b1 &
b1 "
b1 %
1#
#3
b11 !
b11 &
b10 "
b10 %
1#
#4
b111 !
b111 &
b11 "
b11 %
1#
#5
b1111 !
b1111 &
b100 "
b100 %
1#
#6
b11111 !
b11111 &
b101 "
b101 %
1#
#7
b11110 !
b11110 &
b110 "
b110 %
1#
#8
b11100 !
b11100 &
b111 "
b111 %
1#
#9
b11000 !
b11000 &
b1000 "
b1000 %
1#
#10
b10000 !
b10000 &
b1001 "
b1001 %
1#
#11
b0 !
b0 &
b0 "
b0 %
1#
