codifMorse.v
module codifMorse (num, morse, display, reset, ready);

                                                                                                                                                                                                                                                            // A = num[5]
                                                                                                                                                                                                                                                            // B = num[4]
                                                                                                                                                                                                                                                            // C = num[3]
                                                                                                                                                                                                                                                            // D = num [2]
                                                                                                                                                                                                                                                            // E = num[1]
                                                                                                                                                                                                                                                            // F = num[0]

    input reset;
    input ready;
    input wire[5:0] num;
    output reg[4:0] morse;
    output reg[4:0] display;

    always @ (reset) begin
        morse = 0;
    end
    always @ (ready) begin
        if (~reset) begin

          morse[4] <= (num[3] & num[2] & num[1]) | (num[4] & ~num[2] & num[0]) | (num[5] & ~num[1] & ~num[0]) |
                      (~num[5] & ~num[3] & ~num[1] & num[0]) | (~num[5] & ~num[3] & ~num[2] & num[1]) | (~num[4] & ~num[3] & num[2] & ~num[1]) |
                      (~num[4] & num[3] & num[1] & ~num[0]) | (num[4] & num[3] & num[2] & ~num[0]);

          morse[3] <= (num[3] & num[2]) | (~num[4] & num[2] & ~num[1]) | (~num[4] & num[2] & ~num[0]) | (num[5] & ~num[1] & num[0]) | (num[2] & ~num[1] & ~num[0]) |
                      (~num[3] & ~num[2] & num[1] & ~num[0]) | (num[4] & num[2] & num[1] & num[0]) | (~num[5] & ~num[4] & ~num[2] & num[1] & num[0]) |
                      (num[4] & ~num[3] & ~num[2] & ~num[1] & num[0]);

          morse[2] <= (num[5] & num[0]) | (~num[4] & ~num[3] & num[2]) | (num[2] & ~num[1] & num[0]) | (num[3] & ~num[2] & num[1]) | (num[4] & num[2] & num[0]) |
                      (~num[4] & ~num[3] & num[1] & num[0]) | (num[4] & ~num[3] & ~num[2] & ~num[1]) | (num[4] & num[3] & num[2] & ~num[1]);

          morse[1] <= (~num[4] & num[2]) | (num[4] & ~num[1]) | (~num[4] & num[3] & ~num[0]) | (~num[4] & num[3] & num[1]) | (num[5] & num[1] & num[0]);

          morse[0] <= (num[3]) | (num[2] & num[0]) | (num[2] & num[1]);


          display[4] <= 1;

          display[3] <= (~num[3]) | (~num[2]) | (~num[4] & ~num[1]) | (num[1] & num[0]) | (num[4] & ~num[0]);

          display[2] <= (~num[1] & ~num[0]) | (~num[4] & ~num[3]) | (~num[3] & ~num[1]) | (~num[2] & num[0]) | (~num[4] & num[0]) | (num[4] & num[3] & num[1]);

          display[1] <= (num[5] & num[1]) | (~num[5] & ~num[4] & ~num[3]) | (~num[4] & ~num[2] & num[0]) | (~num[3] & ~num[2] & num[0]) | (~num[3] & ~num[1] & num[0]) |
                        (~num[2] & ~num[1] & num[0]) | (~num[5] & ~num[4] & ~num[1] & ~num[0]) | (num[3] & num[2] & num[1] & num[0]) | (num[4] & num[3] & ~num[2] & num[1] & ~num[0]);

          display[0] <= (~num[5] & ~num[4] & ~num[3]) | (~num[5] & ~num[4] & ~num[2] & ~num[1]);

        end
    end
endmodule // divisivel

module demuxDisplay (num, display, ponto, traco, ready);

    input wire[4:0] num;
    input wire[4:0] display;
    input wire ready;

    output wire[4:0] ponto;
    output wire[4:0] traco;

    assign  traco[4] = (display[4] & ~num[4]);
    assign  ponto[4] = (display[4] & num[4]);

    assign  traco[3] = (display[3] & ~num[3]);
    assign  ponto[3] = (display[3] & num[3]);

    assign  traco[2] = (display[2] & ~num[2]);
    assign  ponto[2] = (display[2] & num[2]);

    assign  traco[1] = (display[1] & ~num[1]);
    assign  ponto[1] = (display[1] & num[1]);

    assign  traco[0] = (display[0] & ~num[0]);
    assign  ponto[0] = (display[0] & num[0]);


endmodule

testbench.v
`include "codifMorse.v"

module testbench ();
    reg[5:0] num;
    reg rst, rdy;
    wire[4:0] morse;
    wire[4:0] display;
    wire[4:0] ponto;
    wire[4:0] traco;

    codifMorse codificador (.num(num), .display(display), .reset(rst), .ready(rdy), .morse(morse));
    demuxDisplay demux4 (.num(morse), .display(display), .ponto(ponto), .traco(traco), .ready(rdy));

    initial begin
      $dumpfile("codifMorse.vcd");
      $dumpvars(0, testbench);
      $display("\nNúmero -- Equivalente em morse:\n");
      $monitor("   [PONTO] = %b %b %b %b %b \n   [TRACO] = %b %b %b %b %b \n", ponto[4], ponto[3], ponto[2], ponto[1], ponto[0], traco[4], traco[3], traco[2], traco[1], traco[0]);

      rst = 1; rst = 0;
      rdy = 0; num = 1; rdy = 1;
      $display("\n   [CARACTERE] = %d",num);
      #1; rdy = 0; num = 2; rdy = 1;
      $display("\n   [CARACTERE] = %d",num);
      #1; rdy = 0; num = 3; rdy = 1;
      $display("\n   [CARACTERE] = %d",num);
      #1; rdy = 0; num = 4; rdy = 1;
      $display("\n   [CARACTERE] = %d",num);
      #1; rdy = 0; num = 5; rdy = 1;
      $display("\n   [CARACTERE] = %d",num);
      #1; rdy = 0; num = 6; rdy = 1;
      $display("\n   [CARACTERE] = %d",num);
      #1; rdy = 0; num = 7; rdy = 1;
      $display("\n   [CARACTERE] = %d",num);
      #1; rdy = 0; num = 8; rdy = 1;
      $display("\n   [CARACTERE] = %d",num);
      #1; rdy = 0; num = 9; rdy = 1;
      $display("\n   [CARACTERE] = %d",num);
      #1; rdy = 0; num = 0; rdy = 1;
      $display("\n   [CARACTERE] = %d",num);
      #1; rdy = 0; num = 10; rdy = 1;
      $display("\n   [CARACTERE] = A");
      #1; rdy = 0; num = 11; rdy = 1;
      $display("\n   [CARACTERE] = B");
      #1; rdy = 0; num = 12; rdy = 1;
      $display("\n   [CARACTERE] = C");
      #1; rdy = 0; num = 13; rdy = 1;
      $display("\n   [CARACTERE] = D");
      #1; rdy = 0; num = 14; rdy = 1;
      $display("\n   [CARACTERE] = E");
      #1; rdy = 0; num = 15; rdy = 1;
      $display("\n   [CARACTERE] = F");
      #1; rdy = 0; num = 16; rdy = 1;
      $display("\n   [CARACTERE] = G");
      #1; rdy = 0; num = 17; rdy = 1;
      $display("\n   [CARACTERE] = H");
      #1; rdy = 0; num = 18; rdy = 1;
      $display("\n   [CARACTERE] = I");
      #1; rdy = 0; num = 19; rdy = 1;
      $display("\n   [CARACTERE] = J");
      #1; rdy = 0; num = 20; rdy = 1;
      $display("\n   [CARACTERE] = K");
      #1; rdy = 0; num = 21; rdy = 1;
      $display("\n   [CARACTERE] = L");
      #1; rdy = 0; num = 22; rdy = 1;
      $display("\n   [CARACTERE] = M");
      #1; rdy = 0; num = 23; rdy = 1;
      $display("\n   [CARACTERE] = N");
      #1; rdy = 0; num = 24; rdy = 1;
      $display("\n   [CARACTERE] = O");
      #1; rdy = 0; num = 25; rdy = 1;
      $display("\n   [CARACTERE] = P");
      #1; rdy = 0; num = 26; rdy = 1;
      $display("\n   [CARACTERE] = Q");
      #1; rdy = 0; num = 27; rdy = 1;
      $display("\n   [CARACTERE] = R");
      #1; rdy = 0; num = 28; rdy = 1;
      $display("\n   [CARACTERE] = S");
      #1; rdy = 0; num = 29; rdy = 1;
      $display("\n   [CARACTERE] = T");
      #1; rdy = 0; num = 30; rdy = 1;
      $display("\n   [CARACTERE] = U");
      #1; rdy = 0; num = 31; rdy = 1;
      $display("\n   [CARACTERE] = V");
      #1; rdy = 0; num = 32; rdy = 1;
      $display("\n   [CARACTERE] = W");
      #1; rdy = 0; num = 33; rdy = 1;
      $display("\n   [CARACTERE] = X");
      #1; rdy = 0; num = 34; rdy = 1;
      $display("\n   [CARACTERE] = Y");
      #1; rdy = 0; num = 35; rdy = 1;
      $display("\n   [CARACTERE] = Z");
      #1;

      $finish;

    end
endmodule // testbench

codifMorse.vcd
$date
	Fri Oct  5 20:56:32 2018
$end
$version
	Icarus Verilog
$end
$timescale
	1s
$end
$scope module testbench $end
$var wire 5 ! traco [4:0] $end
$var wire 5 " ponto [4:0] $end
$var wire 5 # morse [4:0] $end
$var wire 5 $ display [4:0] $end
$var reg 6 % num [5:0] $end
$var reg 1 & rdy $end
$var reg 1 ' rst $end
$scope module codificador $end
$var wire 6 ( num [5:0] $end
$var wire 1 & ready $end
$var wire 1 ' reset $end
$var reg 5 ) display [4:0] $end
$var reg 5 * morse [4:0] $end
$upscope $end
$scope module demux4 $end
$var wire 5 + display [4:0] $end
$var wire 5 , num [4:0] $end
$var wire 1 & ready $end
$var wire 5 - traco [4:0] $end
$var wire 5 . ponto [4:0] $end
$upscope $end
$upscope $end
$enddefinitions $end
#0
$dumpvars
b10000 .
b1111 -
b10000 ,
b11111 +
b10000 *
b11111 )
b1 (
0'
1&
b1 %
b11111 $
b10000 #
b10000 "
b1111 !
$end
#1
b111 !
b111 -
b11000 "
b11000 .
b11000 #
b11000 *
b11000 ,
b10 %
b10 (
1&
#2
b11 !
b11 -
b11100 "
b11100 .
b11100 #
b11100 *
b11100 ,
b11 %
b11 (
1&
#3
b1 !
b1 -
b11110 "
b11110 .
b11110 #
b11110 *
b11110 ,
b100 %
b100 (
1&
#4
b0 !
b0 -
b11111 "
b11111 .
b11111 #
b11111 *
b11111 ,
b101 %
b101 (
1&
#5
b10000 !
b10000 -
b1111 "
b1111 .
b1111 #
b1111 *
b1111 ,
b110 %
b110 (
1&
#6
b11000 !
b11000 -
b111 "
b111 .
b111 #
b111 *
b111 ,
b111 %
b111 (
1&
#7
b11100 !
b11100 -
b11 "
b11 .
b11 #
b11 *
b11 ,
b1000 %
b1000 (
1&
#8
b11110 !
b11110 -
b1 "
b1 .
b1 #
b1 *
b1 ,
b1001 %
b1001 (
1&
#9
b11111 !
b11111 -
b0 "
b0 .
b0 #
b0 *
b0 ,
b0 %
b0 (
1&
#10
b1000 !
b1000 -
b10000 "
b10000 .
b11000 $
b11000 )
b11000 +
b10111 #
b10111 *
b10111 ,
b1010 %
b1010 (
1&
#11
b10000 !
b10000 -
b1110 "
b1110 .
b11110 $
b11110 )
b11110 +
b1111 #
b1111 *
b1111 ,
b1011 %
b1011 (
1&
#12
b10100 !
b10100 -
b1010 "
b1010 .
b1011 #
b1011 *
b1011 ,
b1100 %
b1100 (
1&
#13
b10000 !
b10000 -
b1100 "
b1100 .
b11100 $
b11100 )
b11100 +
b1111 #
b1111 *
b1111 ,
b1101 %
b1101 (
1&
#14
b0 !
b0 -
b10000 "
b10000 .
b10000 $
b10000 )
b10000 +
b11011 #
b11011 *
b11011 ,
b1110 %
b1110 (
1&
#15
b100 !
b100 -
b11010 "
b11010 .
b11110 $
b11110 )
b11110 +
b1111 %
b1111 (
1&
#16
b11000 !
b11000 -
b100 "
b100 .
b11100 $
b11100 )
b11100 +
b110 #
b110 *
b110 ,
b10000 %
b10000 (
1&
#17
b0 !
b0 -
b11110 "
b11110 .
b11110 $
b11110 )
b11110 +
b11110 #
b11110 *
b11110 ,
b10001 %
b10001 (
1&
#18
b11000 "
b11000 .
b11000 $
b11000 )
b11000 +
b11000 #
b11000 *
b11000 ,
b10010 %
b10010 (
1&
#19
b1110 !
b1110 -
b10000 "
b10000 .
b11110 $
b11110 )
b11110 +
b10000 #
b10000 *
b10000 ,
b10011 %
b10011 (
1&
#20
b10100 !
b10100 -
b1000 "
b1000 .
b11100 $
b11100 )
b11100 +
b1010 #
b1010 *
b1010 ,
b10100 %
b10100 (
1&
#21
b1000 !
b1000 -
b10110 "
b10110 .
b11110 $
b11110 )
b11110 +
b10111 #
b10111 *
b10111 ,
b10101 %
b10101 (
1&
#22
b11000 !
b11000 -
b0 "
b0 .
b11000 $
b11000 )
b11000 +
b1 #
b1 *
b1 ,
b10110 %
b10110 (
1&
#23
b10000 !
b10000 -
b1000 "
b1000 .
b1101 #
b1101 *
b1101 ,
b10111 %
b10111 (
1&
#24
b11100 !
b11100 -
b0 "
b0 .
b11100 $
b11100 )
b11100 +
b11 #
b11 *
b11 ,
b11000 %
b11000 (
1&
#25
b1100 !
b1100 -
b10010 "
b10010 .
b11110 $
b11110 )
b11110 +
b10011 #
b10011 *
b10011 ,
b11001 %
b11001 (
1&
#26
b11010 !
b11010 -
b100 "
b100 .
b101 #
b101 *
b101 ,
b11010 %
b11010 (
1&
#27
b1000 !
b1000 -
b10100 "
b10100 .
b11100 $
b11100 )
b11100 +
b10101 #
b10101 *
b10101 ,
b11011 %
b11011 (
1&
#28
b0 !
b0 -
b11100 "
b11100 .
b11111 #
b11111 *
b11111 ,
b11100 %
b11100 (
1&
#29
b10000 !
b10000 -
b0 "
b0 .
b10000 $
b10000 )
b10000 +
b1111 #
b1111 *
b1111 ,
b11101 %
b11101 (
1&
#30
b100 !
b100 -
b11000 "
b11000 .
b11100 $
b11100 )
b11100 +
b11001 #
b11001 *
b11001 ,
b11110 %
b11110 (
1&
#31
b10 !
b10 -
b11100 "
b11100 .
b11110 $
b11110 )
b11110 +
b11101 #
b11101 *
b11101 ,
b11111 %
b11111 (
1&
#32
b1100 !
b1100 -
b10000 "
b10000 .
b11100 $
b11100 )
b11100 +
b10000 #
b10000 *
b10000 ,
b100000 %
b100000 (
1&
#33
b10010 !
b10010 -
b1100 "
b1100 .
b11110 $
b11110 )
b11110 +
b1100 #
b1100 *
b1100 ,
b100001 %
b100001 (
1&
#34
b10110 !
b10110 -
b1000 "
b1000 .
b1000 #
b1000 *
b1000 ,
b100010 %
b100010 (
1&
#35
b11000 !
b11000 -
b110 "
b110 .
b110 #
b110 *
b110 ,
b100011 %
b100011 (
1&
