codifMorse.v
module codifMorse (num, morse, display, reset, ready);

// Equivalentes aos mapas de Karnaugh e equacoes booleanas:
// A = num[5]
// B = num[4]
// C = num[3]
// D = num[2]
// E = num[1]
// F = num[0]

    input reset;
    input ready;
    input wire[5:0] num;
    output reg[4:0] morse;
    output reg[4:0] display;

    always @(ready, ready) begin
        if (~reset & ready) begin
	
	  //morse[x] indica se o morse é um ponto (sinal verdadeiro) ou traco (sinal falso)
          morse[4] <= (num[3] & num[2] & num[1]) | (num[4] & ~num[2] & num[0]) | (num[5] & ~num[1] & ~num[0]) |
                      (~num[5] & ~num[3] & ~num[1] & num[0]) | (~num[5] & ~num[3] & ~num[2] & num[1]) | (~num[4] & ~num[3] & num[2] & ~num[1]) |
                      (~num[4] & num[3] & num[1] & ~num[0]) | (num[4] & num[3] & num[2] & ~num[0]);

          morse[3] <= (num[3] & num[2]) | (~num[4] & num[2] & ~num[1]) | (~num[4] & num[2] & ~num[0]) | (num[5] & ~num[1] & num[0]) | (num[2] & ~num[1] & ~num[0]) |
                      (~num[3] & ~num[2] & num[1] & ~num[0]) | (num[4] & num[2] & num[1] & num[0]) | (~num[5] & ~num[4] & ~num[2] & num[1] & num[0]) |
                      (num[4] & ~num[3] & ~num[2] & ~num[1] & num[0]);

          morse[2] <= (num[5] & num[0]) | (~num[4] & ~num[3] & num[2]) | (num[2] & ~num[1] & num[0]) | (num[3] & ~num[2] & num[1]) | (num[4] & num[2] & num[0]) |
                      (~num[4] & ~num[3] & num[1] & num[0]) | (num[4] & ~num[3] & ~num[2] & ~num[1]) | (num[4] & num[3] & num[2] & ~num[1]);

          morse[1] <= (~num[4] & num[2]) | (num[4] & ~num[1]) | (~num[4] & num[3] & ~num[0]) | (~num[4] & num[3] & num[1]) | (num[5] & num[1] & num[0]);

          morse[0] <= (num[3]) | (num[2] & num[0]) | (num[2] & num[1]);


	  //display[x] indica que aquele ponto/traco deve ser considerado ou nao. Verdadeiro se sim, falso se nao
          display[4] <= 1;

          display[3] <= (~num[3]) | (~num[2]) | (~num[4] & ~num[1]) | (num[1] & num[0]) | (num[4] & ~num[0]);

          display[2] <= (~num[1] & ~num[0]) | (~num[4] & ~num[3]) | (~num[3] & ~num[1]) | (~num[2] & num[0]) | (~num[4] & num[0]) | (num[4] & num[3] & num[1]);

          display[1] <= (num[5] & num[1]) | (~num[5] & ~num[4] & ~num[3]) | (~num[4] & ~num[2] & num[0]) | (~num[3] & ~num[2] & num[0]) | (~num[3] & ~num[1] & num[0]) |
                        (~num[2] & ~num[1] & num[0]) | (~num[5] & ~num[4] & ~num[1] & ~num[0]) | (num[3] & num[2] & num[1] & num[0]) | (num[4] & num[3] & ~num[2] & num[1] & ~num[0]);

          display[0] <= (~num[5] & ~num[4] & ~num[3]) | (~num[5] & ~num[4] & ~num[2] & ~num[1]);

        end

      if(reset) begin
         morse[4] <= 0;
  	 morse[3] <= 0;
  	 morse[2] <= 0;
  	 morse[1] <= 0;
  	 morse[0] <= 0;

      end

    end

endmodule

module demuxDisplay (
    //modulo responsavel por transformar uma entrada de morse[x] em display[x] nas saidas para serem ligadas onde sera representado ponto e o traco
    input wire num,
    input wire display,
    input wire ready,

    output wire ponto,
    output wire traco
);

    assign  traco = (display & ~num);
    assign  ponto = (display & num);


endmodule

module sevSeg(
	 //modulo inversor necessario pois na FPGA 1 e desligado, 0 ligado
	 input wire ponto,
	 input wire traco,
	 output wire [6:0] display
	 );

	 assign display[0] = 1;
	 assign display[1] = 1;
	 assign display[2] = 1;
	 assign display[3] = ~ponto;
	 assign display[4] = 1;
	 assign display[5] = 1;
	 assign display[6] = ~traco;

endmodule

module desligaSeg(output wire [6:0] display);
	 //desliga totalmente um display da FPGA
	 assign display[0] = 1;
	 assign display[1] = 1;
	 assign display[2] = 1;
	 assign display[3] = 1;
	 assign display[4] = 1;
	 assign display[5] = 1;
	 assign display[6] = 1;

endmodule

testbench.v
`include "codifMorse.v"

module testbench ();
    reg[5:0] num;
    reg rst, rdy;
    wire[4:0] morse;
    wire[4:0] display;
    wire[4:0] ponto;
    wire[4:0] traco;

    codifMorse codificador (.num(num), .display(display), .reset(rst), .ready(rdy), .morse(morse));
    demuxDisplay demux4 (.num(morse[4]), .display(display[4]), .ponto(ponto[4]), .traco(traco[4]));
    demuxDisplay demux3 (.num(morse[3]), .display(display[3]), .ponto(ponto[3]), .traco(traco[3]));
    demuxDisplay demux2 (.num(morse[2]), .display(display[2]), .ponto(ponto[2]), .traco(traco[2]));
    demuxDisplay demux1 (.num(morse[1]), .display(display[1]), .ponto(ponto[1]), .traco(traco[1]));
    demuxDisplay demux0 (.num(morse[0]), .display(display[0]), .ponto(ponto[0]), .traco(traco[0]));

    initial begin
      $dumpfile("codifMorse.vcd");
      $dumpvars(0, testbench);
      $display("\nNúmero -- Equivalente em morse:\n");

      rst = 1; rst = 0;

rdy = 0; num = 1; rdy = 1; #1;
      $display("\n   [CARACTERE] = %d",num);
      $display("   [PONTO] = %b %b %b %b %b \n   [TRACO] = %b %b %b %b %b \n", ponto[4], ponto[3], ponto[2], ponto[1], ponto[0], traco[4], traco[3], traco[2], traco[1], traco[0]);
    
rdy = 0; num = 2; rdy = 1; #1;
      $display("\n   [CARACTERE] = %d",num);
      $display("   [PONTO] = %b %b %b %b %b \n   [TRACO] = %b %b %b %b %b \n", ponto[4], ponto[3], ponto[2], ponto[1], ponto[0], traco[4], traco[3], traco[2], traco[1], traco[0]);

rdy = 0; num = 3; rdy = 1; #1;
      $display("\n   [CARACTERE] = %d",num);
      $display("   [PONTO] = %b %b %b %b %b \n   [TRACO] = %b %b %b %b %b \n", ponto[4], ponto[3], ponto[2], ponto[1], ponto[0], traco[4], traco[3], traco[2], traco[1], traco[0]);

rdy = 0; num = 4; rdy = 1; #1;
      $display("\n   [CARACTERE] = %d",num);
      $display("   [PONTO] = %b %b %b %b %b \n   [TRACO] = %b %b %b %b %b \n", ponto[4], ponto[3], ponto[2], ponto[1], ponto[0], traco[4], traco[3], traco[2], traco[1], traco[0]);

rdy = 0; num = 5; rdy = 1; #1;
      $display("\n   [CARACTERE] = %d",num);
      $display("   [PONTO] = %b %b %b %b %b \n   [TRACO] = %b %b %b %b %b \n", ponto[4], ponto[3], ponto[2], ponto[1], ponto[0], traco[4], traco[3], traco[2], traco[1], traco[0]);

rdy = 0; num = 6; rdy = 1; #1;
      $display("\n   [CARACTERE] = %d",num);
      $display("   [PONTO] = %b %b %b %b %b \n   [TRACO] = %b %b %b %b %b \n", ponto[4], ponto[3], ponto[2], ponto[1], ponto[0], traco[4], traco[3], traco[2], traco[1], traco[0]);

rdy = 0; num = 7; rdy = 1; #1;
      $display("\n   [CARACTERE] = %d",num);
      $display("   [PONTO] = %b %b %b %b %b \n   [TRACO] = %b %b %b %b %b \n", ponto[4], ponto[3], ponto[2], ponto[1], ponto[0], traco[4], traco[3], traco[2], traco[1], traco[0]);

rdy = 0; num = 8; rdy = 1; #1;
      $display("\n   [CARACTERE] = %d",num);
      $display("   [PONTO] = %b %b %b %b %b \n   [TRACO] = %b %b %b %b %b \n", ponto[4], ponto[3], ponto[2], ponto[1], ponto[0], traco[4], traco[3], traco[2], traco[1], traco[0]);

rdy = 0; num = 9; rdy = 1; #1;
      $display("\n   [CARACTERE] = %d",num);

      $display("   [PONTO] = %b %b %b %b %b \n   [TRACO] = %b %b %b %b %b \n", ponto[4], ponto[3], ponto[2], ponto[1], ponto[0], traco[4], traco[3], traco[2], traco[1], traco[0]);

rdy = 0; num = 0; rdy = 1; #1;
      $display("\n   [CARACTERE] = %d",num);
      $display("   [PONTO] = %b %b %b %b %b \n   [TRACO] = %b %b %b %b %b \n", ponto[4], ponto[3], ponto[2], ponto[1], ponto[0], traco[4], traco[3], traco[2], traco[1], traco[0]);

rdy = 0; num = 10; rdy = 1; #1;
      $display("\n   [CARACTERE] = A");
      $display("   [PONTO] = %b %b %b %b %b \n   [TRACO] = %b %b %b %b %b \n", ponto[4], ponto[3], ponto[2], ponto[1], ponto[0], traco[4], traco[3], traco[2], traco[1], traco[0]);
rdy = 0; num = 11; rdy = 1; #1;
      $display("\n   [CARACTERE] = B");
      $display("   [PONTO] = %b %b %b %b %b \n   [TRACO] = %b %b %b %b %b \n", ponto[4], ponto[3], ponto[2], ponto[1], ponto[0], traco[4], traco[3], traco[2], traco[1], traco[0]);

rdy = 0; num = 12; rdy = 1; #1;
      $display("\n   [CARACTERE] = C");
      $display("   [PONTO] = %b %b %b %b %b \n   [TRACO] = %b %b %b %b %b \n", ponto[4], ponto[3], ponto[2], ponto[1], ponto[0], traco[4], traco[3], traco[2], traco[1], traco[0]);

rdy = 0; num = 13; rdy = 1; #1;
      $display("\n   [CARACTERE] = D");
      $display("   [PONTO] = %b %b %b %b %b \n   [TRACO] = %b %b %b %b %b \n", ponto[4], ponto[3], ponto[2], ponto[1], ponto[0], traco[4], traco[3], traco[2], traco[1], traco[0]);

rdy = 0; num = 14; rdy = 1; #1;
      $display("\n   [CARACTERE] = E");
      $display("   [PONTO] = %b %b %b %b %b \n   [TRACO] = %b %b %b %b %b \n", ponto[4], ponto[3], ponto[2], ponto[1], ponto[0], traco[4], traco[3], traco[2], traco[1], traco[0]);

rdy = 0; num = 15; rdy = 1; #1;
      $display("\n   [CARACTERE] = F");
      $display("   [PONTO] = %b %b %b %b %b \n   [TRACO] = %b %b %b %b %b \n", ponto[4], ponto[3], ponto[2], ponto[1], ponto[0], traco[4], traco[3], traco[2], traco[1], traco[0]);

rdy = 0; num = 16; rdy = 1; #1;
      $display("\n   [CARACTERE] = G");
      $display("   [PONTO] = %b %b %b %b %b \n   [TRACO] = %b %b %b %b %b \n", ponto[4], ponto[3], ponto[2], ponto[1], ponto[0], traco[4], traco[3], traco[2], traco[1], traco[0]);

rdy = 0; num = 17; rdy = 1; #1;
      $display("\n   [CARACTERE] = H");
      $display("   [PONTO] = %b %b %b %b %b \n   [TRACO] = %b %b %b %b %b \n", ponto[4], ponto[3], ponto[2], ponto[1], ponto[0], traco[4], traco[3], traco[2], traco[1], traco[0]);

rdy = 0; num = 18; rdy = 1; #1;
      $display("\n   [CARACTERE] = I");
      $display("   [PONTO] = %b %b %b %b %b \n   [TRACO] = %b %b %b %b %b \n", ponto[4], ponto[3], ponto[2], ponto[1], ponto[0], traco[4], traco[3], traco[2], traco[1], traco[0]);

rdy = 0; num = 19; rdy = 1; #1;
      $display("\n   [CARACTERE] = J");
      $display("   [PONTO] = %b %b %b %b %b \n   [TRACO] = %b %b %b %b %b \n", ponto[4], ponto[3], ponto[2], ponto[1], ponto[0], traco[4], traco[3], traco[2], traco[1], traco[0]);

rdy = 0; num = 20; rdy = 1; #1;
      $display("\n   [CARACTERE] = K");
      $display("   [PONTO] = %b %b %b %b %b \n   [TRACO] = %b %b %b %b %b \n", ponto[4], ponto[3], ponto[2], ponto[1], ponto[0], traco[4], traco[3], traco[2], traco[1], traco[0]);

rdy = 0; num = 21; rdy = 1; #1;
      $display("\n   [CARACTERE] = L");
      $display("   [PONTO] = %b %b %b %b %b \n   [TRACO] = %b %b %b %b %b \n", ponto[4], ponto[3], ponto[2], ponto[1], ponto[0], traco[4], traco[3], traco[2], traco[1], traco[0]);

rdy = 0; num = 22; rdy = 1; #1;
      $display("\n   [CARACTERE] = M");
      $display("   [PONTO] = %b %b %b %b %b \n   [TRACO] = %b %b %b %b %b \n", ponto[4], ponto[3], ponto[2], ponto[1], ponto[0], traco[4], traco[3], traco[2], traco[1], traco[0]);

rdy = 0; num = 23; rdy = 1; #1;
      $display("\n   [CARACTERE] = N");
      $display("   [PONTO] = %b %b %b %b %b \n   [TRACO] = %b %b %b %b %b \n", ponto[4], ponto[3], ponto[2], ponto[1], ponto[0], traco[4], traco[3], traco[2], traco[1], traco[0]);

rdy = 0; num = 24; rdy = 1; #1;
      $display("\n   [CARACTERE] = O");
      $display("   [PONTO] = %b %b %b %b %b \n   [TRACO] = %b %b %b %b %b \n", ponto[4], ponto[3], ponto[2], ponto[1], ponto[0], traco[4], traco[3], traco[2], traco[1], traco[0]);

rdy = 0; num = 25; rdy = 1; #1;
      $display("\n   [CARACTERE] = P");
      $display("   [PONTO] = %b %b %b %b %b \n   [TRACO] = %b %b %b %b %b \n", ponto[4], ponto[3], ponto[2], ponto[1], ponto[0], traco[4], traco[3], traco[2], traco[1], traco[0]);

rdy = 0; num = 26; rdy = 1; #1;
      $display("\n   [CARACTERE] = Q");
      $display("   [PONTO] = %b %b %b %b %b \n   [TRACO] = %b %b %b %b %b \n", ponto[4], ponto[3], ponto[2], ponto[1], ponto[0], traco[4], traco[3], traco[2], traco[1], traco[0]);

rdy = 0; num = 27; rdy = 1; #1;
      $display("\n   [CARACTERE] = R");
      $display("   [PONTO] = %b %b %b %b %b \n   [TRACO] = %b %b %b %b %b \n", ponto[4], ponto[3], ponto[2], ponto[1], ponto[0], traco[4], traco[3], traco[2], traco[1], traco[0]);

rdy = 0; num = 28; rdy = 1; #1;
      $display("\n   [CARACTERE] = S");
      $display("   [PONTO] = %b %b %b %b %b \n   [TRACO] = %b %b %b %b %b \n", ponto[4], ponto[3], ponto[2], ponto[1], ponto[0], traco[4], traco[3], traco[2], traco[1], traco[0]);

rdy = 0; num = 29; rdy = 1; #1;
      $display("\n   [CARACTERE] = T");
      $display("   [PONTO] = %b %b %b %b %b \n   [TRACO] = %b %b %b %b %b \n", ponto[4], ponto[3], ponto[2], ponto[1], ponto[0], traco[4], traco[3], traco[2], traco[1], traco[0]);

rdy = 0; num = 30; rdy = 1; #1;
      $display("\n   [CARACTERE] = U");
      $display("   [PONTO] = %b %b %b %b %b \n   [TRACO] = %b %b %b %b %b \n", ponto[4], ponto[3], ponto[2], ponto[1], ponto[0], traco[4], traco[3], traco[2], traco[1], traco[0]);

rdy = 0; num = 31; rdy = 1; #1;
      $display("\n   [CARACTERE] = V");
      $display("   [PONTO] = %b %b %b %b %b \n   [TRACO] = %b %b %b %b %b \n", ponto[4], ponto[3], ponto[2], ponto[1], ponto[0], traco[4], traco[3], traco[2], traco[1], traco[0]);

rdy = 0; num = 32; rdy = 1; #1;
      $display("\n   [CARACTERE] = W");
      $display("   [PONTO] = %b %b %b %b %b \n   [TRACO] = %b %b %b %b %b \n", ponto[4], ponto[3], ponto[2], ponto[1], ponto[0], traco[4], traco[3], traco[2], traco[1], traco[0]);

rdy = 0; num = 33; rdy = 1; #1;
      $display("\n   [CARACTERE] = X");
      $display("   [PONTO] = %b %b %b %b %b \n   [TRACO] = %b %b %b %b %b \n", ponto[4], ponto[3], ponto[2], ponto[1], ponto[0], traco[4], traco[3], traco[2], traco[1], traco[0]);

rdy = 0; num = 34; rdy = 1; #1;
      $display("\n   [CARACTERE] = Y");
      $display("   [PONTO] = %b %b %b %b %b \n   [TRACO] = %b %b %b %b %b \n", ponto[4], ponto[3], ponto[2], ponto[1], ponto[0], traco[4], traco[3], traco[2], traco[1], traco[0]);

rdy = 0; num = 35; rdy = 1; #1;
      $display("\n   [CARACTERE] = Z");
      $display("   [PONTO] = %b %b %b %b %b \n   [TRACO] = %b %b %b %b %b \n", ponto[4], ponto[3], ponto[2], ponto[1], ponto[0], traco[4], traco[3], traco[2], traco[1], traco[0]);
      $finish;

    end
endmodule // testbench

codifMorse.vcd
$date
	Sat Oct 06 11:06:06 2018
$end
$version
	Icarus Verilog
$end
$timescale
	1s
$end
$scope module testbench $end
$var wire 5 ! traco [4:0] $end
$var wire 5 " ponto [4:0] $end
$var wire 5 # morse [4:0] $end
$var wire 5 $ display [4:0] $end
$var reg 6 % num [5:0] $end
$var reg 1 & rdy $end
$var reg 1 ' rst $end
$scope module codificador $end
$var wire 6 ( num [5:0] $end
$var wire 1 & ready $end
$var wire 1 ' reset $end
$var reg 5 ) display [4:0] $end
$var reg 5 * morse [4:0] $end
$upscope $end
$scope module demux0 $end
$var wire 1 + display $end
$var wire 1 , num $end
$var wire 1 - ponto $end
$var wire 1 . ready $end
$var wire 1 / traco $end
$upscope $end
$scope module demux1 $end
$var wire 1 0 display $end
$var wire 1 1 num $end
$var wire 1 2 ponto $end
$var wire 1 3 ready $end
$var wire 1 4 traco $end
$upscope $end
$scope module demux2 $end
$var wire 1 5 display $end
$var wire 1 6 num $end
$var wire 1 7 ponto $end
$var wire 1 8 ready $end
$var wire 1 9 traco $end
$upscope $end
$scope module demux3 $end
$var wire 1 : display $end
$var wire 1 ; num $end
$var wire 1 < ponto $end
$var wire 1 = ready $end
$var wire 1 > traco $end
$upscope $end
$scope module demux4 $end
$var wire 1 ? display $end
$var wire 1 @ num $end
$var wire 1 A ponto $end
$var wire 1 B ready $end
$var wire 1 C traco $end
$upscope $end
$upscope $end
$enddefinitions $end
#0
$dumpvars
0C
zB
1A
1@
1?
1>
z=
0<
0;
1:
19
z8
07
06
15
14
z3
02
01
10
1/
z.
0-
0,
1+
b10000 *
b11111 )
b1 (
0'
1&
b1 %
b11111 $
b10000 #
b10000 "
b1111 !
$end
#1
b111 !
0>
b11000 "
1<
1;
b11000 #
b11000 *
b10 %
b10 (
1&
#2
b11 !
09
b11100 "
17
16
b11100 #
b11100 *
b11 %
b11 (
1&
#3
b1 !
04
b11110 "
12
11
b11110 #
b11110 *
b100 %
b100 (
1&
#4
b0 !
0/
b11111 "
1-
1,
b11111 #
b11111 *
b101 %
b101 (
1&
#5
b10000 !
1C
b1111 "
0A
0@
b1111 #
b1111 *
b110 %
b110 (
1&
#6
b11000 !
1>
b111 "
0<
0;
b111 #
b111 *
b111 %
b111 (
1&
#7
b11100 !
19
b11 "
07
06
b11 #
b11 *
b1000 %
b1000 (
1&
#8
b11110 !
14
b1 "
02
01
b1 #
b1 *
b1001 %
b1001 (
1&
#9
b11111 !
1/
b0 "
0-
0,
b0 #
b0 *
b0 %
b0 (
1&
#10
0C
0/
04
b1000 !
09
b10000 "
1A
0+
00
05
1,
11
16
1@
b11000 $
b11000 )
b10111 #
b10111 *
b1010 %
b1010 (
1&
#11
0>
b10000 !
1C
12
17
1<
b1110 "
0A
10
15
1;
0@
b11110 $
b11110 )
b1111 #
b1111 *
b1011 %
b1011 (
1&
#12
b10100 !
19
b1010 "
07
06
b1011 #
b1011 *
b1100 %
b1100 (
1&
#13
b10000 !
09
02
b1100 "
17
00
16
b11100 $
b11100 )
b1111 #
b1111 *
b1101 %
b1101 (
1&
#14
b0 !
0C
0<
07
b10000 "
1A
05
0:
06
1@
b10000 $
b10000 )
b11011 #
b11011 *
b1110 %
b1110 (
1&
#15
12
b100 !
19
b11010 "
1<
10
15
1:
b11110 $
b11110 )
b1111 %
b1111 (
1&
#16
09
1>
b11000 !
1C
02
17
0<
b100 "
0A
00
0,
16
0;
0@
b11100 $
b11100 )
b110 #
b110 *
b10000 %
b10000 (
1&
#17
0>
b0 !
0C
12
1<
b11110 "
1A
10
1;
1@
b11110 $
b11110 )
b11110 #
b11110 *
b10001 %
b10001 (
1&
#18
02
b11000 "
07
00
05
01
06
b11000 $
b11000 )
b11000 #
b11000 *
b10010 %
b10010 (
1&
#19
1>
14
b1110 !
19
b10000 "
0<
10
15
0;
b11110 $
b11110 )
b10000 #
b10000 *
b10011 %
b10011 (
1&
#20
0>
1C
b10100 !
04
1<
b1000 "
0A
00
11
1;
0@
b11100 $
b11100 )
b1010 #
b1010 *
b10100 %
b10100 (
1&
#21
09
1>
b1000 !
0C
12
17
0<
b10110 "
1A
10
1,
16
0;
1@
b11110 $
b11110 )
b10111 #
b10111 *
b10101 %
b10101 (
1&
#22
b11000 !
1C
02
07
b0 "
0A
00
05
01
06
0@
b11000 $
b11000 )
b1 #
b1 *
b10110 %
b10110 (
1&
#23
b10000 !
0>
b1000 "
1<
16
1;
b1101 #
b1101 *
b10111 %
b10111 (
1&
#24
1>
b11100 !
19
b0 "
0<
15
11
06
0;
b11100 $
b11100 )
b11 #
b11 *
b11000 %
b11000 (
1&
#25
b1100 !
0C
12
b10010 "
1A
10
1@
b11110 $
b11110 )
b10011 #
b10011 *
b11001 %
b11001 (
1&
#26
14
09
b11010 !
1C
02
17
b100 "
0A
01
16
0@
b101 #
b101 *
b11010 %
b11010 (
1&
#27
0C
b1000 !
04
b10100 "
1A
00
1@
b11100 $
b11100 )
b10101 #
b10101 *
b11011 %
b11011 (
1&
#28
b0 !
0>
b11100 "
1<
11
1;
b11111 #
b11111 *
b11100 %
b11100 (
1&
#29
b10000 !
1C
07
0<
b0 "
0A
05
0:
0@
b10000 $
b10000 )
b1111 #
b1111 *
b11101 %
b11101 (
1&
#30
0C
b100 !
19
1<
b11000 "
1A
15
1:
01
06
1@
b11100 $
b11100 )
b11001 #
b11001 *
b11110 %
b11110 (
1&
#31
09
b10 !
14
b11100 "
17
10
16
b11110 $
b11110 )
b11101 #
b11101 *
b11111 %
b11111 (
1&
#32
19
1>
b1100 !
04
07
b10000 "
0<
00
0,
06
0;
b11100 $
b11100 )
b10000 #
b10000 *
b100000 %
b100000 (
1&
#33
09
0>
1C
b10010 !
14
17
1<
b1100 "
0A
10
16
1;
0@
b11110 $
b11110 )
b1100 #
b1100 *
b100001 %
b100001 (
1&
#34
b10110 !
19
b1000 "
07
06
b1000 #
b1000 *
b100010 %
b100010 (
1&
#35
04
09
b11000 !
1>
12
17
b110 "
0<
11
16
0;
b110 #
b110 *
b100011 %
b100011 (
1&
